{
"Certificate Holder" : "KeyBank National Association, as Servicer for Waterfall Finance 10 Grantor Trust, Series I 11501 Outlook Street; Suite 300 Overland Park, KS 66211 #S8335708/M8276124 1 of 1",
"Contact Fax" : "925.482-9390",
"Contact Name" : "Felicia McAroy",
"Contact Phone" : "925.482-9337",
"Insured" : "PAPF Almarida, LLC & Sarum Almarida LLC Argonaut Investments, LLC 101 Larkspur Landing Circle, Ste 120 Larkspur, CA 94939",
"Producer" : "Marsh & McLennan Agency LLC Marsh & McLennan Ins Agency LLC 1340 Treat Blvd #250 Walnut Creek, CA 94597"
}
