[{"page":1,"tables":[{"rows":22,"columns":11,"cells":[{"rowIndex":0,"columnIndex":0,"elements":["#/readResults/0/lines/48/words/0","#/readResults/0/lines/52/words/0"],"boundingBox":[0.3054,4.0741,0.5526,4.066,0.5526,4.2362,0.3054,4.2362],"text":"INSR LTR","rowSpan":0,"columnSpan":0,"confidence":0,"isHeader":false,"isFooter":false},{"rowIndex":0,"columnIndex":1,"elements":[],"boundingBox":[0.5526,4.066,0.7751,4.066,0.7751,4.2362,0.5526,4.2362],"text":"","rowSpan":0,"columnSpan":0,"confidence":0,"isHeader":false,"isFooter":false},{"rowIndex":0,"columnIndex":2,"elements":["#/readResults/0/lines/53/words/0","#/readResults/0/lines/53/words/1","#/readResults/0/lines/53/words/2"],"boundingBox":[0.7751,4.066,2.522,4.0579,2.522,4.2362,0.7751,4.2362],"text":"TYPE OF INSURANCE","rowSpan":0,"columnSpan":2,"confidence":0,"isHeader":false,"isFooter":false},{"rowIndex":0,"columnIndex":4,"elements":["#/readResults/0/lines/49/words/0","#/readResults/0/lines/54/words/0"],"boundingBox":[2.522,4.0579,2.7692,4.0579,2.7692,4.2362,2.522,4.2362],"text":"ADDL INSD","rowSpan":0,"columnSpan":0,"confidence":0,"isHeader":false,"isFooter":false},{"rowIndex":0,"columnIndex":5,"elements":["#/readResults/0/lines/49/words/1","#/readResults/0/lines/54/words/1","#/readResults/0/lines/54/words/2"],"boundingBox":[2.7692,4.0579,3.0329,4.0579,3.0329,4.2281,2.7692,4.2362],"text":"SUBR | WVD","rowSpan":0,"columnSpan":0,"confidence":0,"isHeader":false,"isFooter":false},{"rowIndex":0,"columnIndex":6,"elements":["#/readResults/0/lines/55/words/0","#/readResults/0/lines/55/words/1"],"boundingBox":[3.0329,4.0579,4.7057,4.0579,4.7057,4.2281,3.0329,4.2281],"text":"POLICY NUMBER","rowSpan":0,"columnSpan":0,"confidence":0,"isHeader":false,"isFooter":false},{"rowIndex":0,"columnIndex":7,"elements":["#/readResults/0/lines/50/words/0","#/readResults/0/lines/50/words/1","#/readResults/0/lines/56/words/0"],"boundingBox":[4.7057,4.0579,5.3567,4.0579,5.3567,4.2281,4.7057,4.2281],"text":"POLICY EFF (MM/DD/YYYY)|","rowSpan":0,"columnSpan":0,"confidence":0,"isHeader":false,"isFooter":false},{"rowIndex":0,"columnIndex":8,"elements":["#/readResults/0/lines/51/words/0","#/readResults/0/lines/51/words/1","#/readResults/0/lines/56/words/1"],"boundingBox":[5.3567,4.0579,6.0076,4.0579,6.0076,4.2281,5.3567,4.2281],"text":"POLICY EXP (MM/DD/YYYY)","rowSpan":0,"columnSpan":0,"confidence":0,"isHeader":false,"isFooter":false},{"rowIndex":0,"columnIndex":9,"elements":["#/readResults/0/lines/57/words/0"],"boundingBox":[6.0076,4.0579,8.3478,4.0579,8.3478,4.22,6.0076,4.2281],"text":"LIMITS","rowSpan":0,"columnSpan":2,"confidence":0,"isHeader":false,"isFooter":false},{"rowIndex":1,"columnIndex":0,"elements":["#/readResults/0/lines/58/words/0"],"boundingBox":[0.3054,4.2362,0.5526,4.2362,0.5526,4.4063,0.3054,4.4063],"text":"A","rowSpan":0,"columnSpan":0,"confidence":0,"isHeader":false,"isFooter":false},{"rowIndex":1,"columnIndex":1,"elements":["#/readResults/0/lines/65/words/0","#/readResults/0/selectionMarks/0"],"boundingBox":[0.5526,4.2362,0.7751,4.2362,0.7751,4.4063,0.5526,4.4063],"text":"X","rowSpan":0,"columnSpan":0,"confidence":0,"isHeader":false,"isFooter":false},{"rowIndex":1,"columnIndex":2,"elements":["#/readResults/0/lines/59/words/0","#/readResults/0/lines/59/words/1","#/readResults/0/lines/59/words/2"],"boundingBox":[0.7751,4.2362,2.522,4.2362,2.522,4.3901,0.7751,4.4063],"text":"COMMERCIAL GENERAL LIABILITY","rowSpan":0,"columnSpan":2,"confidence":0,"isHeader":false,"isFooter":false},{"rowIndex":1,"columnIndex":4,"elements":[],"boundingBox":[2.522,4.2362,2.7692,4.2362,2.7692,4.3901,2.522,4.3901],"text":"","rowSpan":0,"columnSpan":0,"confidence":0,"isHeader":false,"isFooter":false},{"rowIndex":1,"columnIndex":5,"elements":[],"boundingBox":[2.7692,4.2362,3.0329,4.2281,3.0329,4.3901,2.7692,4.3901],"text":"","rowSpan":0,"columnSpan":0,"confidence":0,"isHeader":false,"isFooter":false},{"rowIndex":1,"columnIndex":6,"elements":["#/readResults/0/lines/60/words/0"],"boundingBox":[3.0329,4.2281,4.7057,4.2281,4.7057,4.382,3.0329,4.3901],"text":"MAC3142095","rowSpan":0,"columnSpan":0,"confidence":0,"isHeader":false,"isFooter":false},{"rowIndex":1,"columnIndex":7,"elements":["#/readResults/0/lines/61/words/0"],"boundingBox":[4.7057,4.2281,5.3567,4.2281,5.3567,4.3901,4.7057,4.382],"text":"6/1/2021","rowSpan":0,"columnSpan":0,"confidence":0,"isHeader":false,"isFooter":false},{"rowIndex":1,"columnIndex":8,"elements":["#/readResults/0/lines/62/words/0"],"boundingBox":[5.3567,4.2281,6.0076,4.2281,6.0076,4.3901,5.3567,4.3901],"text":"6/1/2022","rowSpan":0,"columnSpan":0,"confidence":0,"isHeader":false,"isFooter":false},{"rowIndex":1,"columnIndex":9,"elements":["#/readResults/0/lines/63/words/0","#/readResults/0/lines/63/words/1"],"boundingBox":[6.0076,4.2281,7.2519,4.22,7.2519,4.3901,6.0076,4.3901],"text":"EACH OCCURRENCE","rowSpan":0,"columnSpan":0,"confidence":0,"isHeader":false,"isFooter":false},{"rowIndex":1,"columnIndex":10,"elements":["#/readResults/0/lines/64/words/0","#/readResults/0/lines/64/words/1"],"boundingBox":[7.2519,4.22,8.3478,4.22,8.3478,4.3901,7.2519,4.3901],"text":"$ 1,000,000","rowSpan":0,"columnSpan":0,"confidence":0,"isHeader":false,"isFooter":false},{"rowIndex":2,"columnIndex":0,"elements":[],"boundingBox":[0.3054,4.4063,0.5526,4.4063,0.5526,4.5765,0.3054,4.5765],"text":"","rowSpan":0,"columnSpan":0,"confidence":0,"isHeader":false,"isFooter":false},{"rowIndex":2,"columnIndex":1,"elements":[],"boundingBox":[0.5526,4.4063,0.7751,4.4063,0.7751,4.5765,0.5526,4.5765],"text":"","rowSpan":0,"columnSpan":0,"confidence":0,"isHeader":false,"isFooter":false},{"rowIndex":2,"columnIndex":2,"elements":["#/readResults/0/lines/66/words/0","#/readResults/0/lines/67/words/0","#/readResults/0/lines/68/words/0","#/readResults/0/selectionMarks/1"],"boundingBox":[0.7751,4.4063,2.522,4.3901,2.522,4.5765,0.7751,4.5765],"text":"X CLAIMS-MADE OCCUR","rowSpan":0,"columnSpan":2,"confidence":0,"isHeader":false,"isFooter":false},{"rowIndex":2,"columnIndex":4,"elements":[],"boundingBox":[2.522,4.3901,2.7692,4.3901,2.7775,4.5765,2.522,4.5765],"text":"","rowSpan":0,"columnSpan":0,"confidence":0,"isHeader":false,"isFooter":false},{"rowIndex":2,"columnIndex":5,"elements":[],"boundingBox":[2.7692,4.3901,3.0329,4.3901,3.0329,4.5765,2.7775,4.5765],"text":"","rowSpan":0,"columnSpan":0,"confidence":0,"isHeader":false,"isFooter":false},{"rowIndex":2,"columnIndex":6,"elements":[],"boundingBox":[3.0329,4.3901,4.7057,4.382,4.7057,4.5765,3.0329,4.5765],"text":"","rowSpan":0,"columnSpan":0,"confidence":0,"isHeader":false,"isFooter":false},{"rowIndex":2,"columnIndex":7,"elements":[],"boundingBox":[4.7057,4.382,5.3567,4.3901,5.3567,4.5765,4.7057,4.5765],"text":"","rowSpan":0,"columnSpan":0,"confidence":0,"isHeader":false,"isFooter":false},{"rowIndex":2,"columnIndex":8,"elements":[],"boundingBox":[5.3567,4.3901,6.0076,4.3901,6.0076,4.5765,5.3567,4.5765],"text":"","rowSpan":0,"columnSpan":0,"confidence":0,"isHeader":false,"isFooter":false},{"rowIndex":2,"columnIndex":9,"elements":["#/readResults/0/lines/69/words/0","#/readResults/0/lines/69/words/1","#/readResults/0/lines/69/words/2","#/readResults/0/lines/70/words/0","#/readResults/0/lines/70/words/1","#/readResults/0/lines/70/words/2"],"boundingBox":[6.0076,4.3901,7.2519,4.3901,7.2519,4.5765,6.0076,4.5765],"text":"DAMAGE TO RENTED PREMISES (Ea occurrence)","rowSpan":0,"columnSpan":0,"confidence":0,"isHeader":false,"isFooter":false},{"rowIndex":2,"columnIndex":10,"elements":["#/readResults/0/lines/71/words/0","#/readResults/0/lines/71/words/1"],"boundingBox":[7.2519,4.3901,8.3478,4.3901,8.3478,4.5765,7.2519,4.5765],"text":"$ 100,000","rowSpan":0,"columnSpan":0,"confidence":0,"isHeader":false,"isFooter":false},{"rowIndex":3,"columnIndex":0,"elements":[],"boundingBox":[0.3054,4.5765,0.5526,4.5765,0.5526,4.7467,0.3054,4.7548],"text":"","rowSpan":0,"columnSpan":0,"confidence":0,"isHeader":false,"isFooter":false},{"rowIndex":3,"columnIndex":1,"elements":["#/readResults/0/lines/72/words/0","#/readResults/0/selectionMarks/2"],"boundingBox":[0.5526,4.5765,0.7751,4.5765,0.7751,4.7467,0.5526,4.7467],"text":"X","rowSpan":0,"columnSpan":0,"confidence":0,"isHeader":false,"isFooter":false},{"rowIndex":3,"columnIndex":2,"elements":["#/readResults/0/lines/73/words/0"],"boundingBox":[0.7751,4.5765,2.522,4.5765,2.522,4.7548,0.7751,4.7467],"text":"0","rowSpan":0,"columnSpan":2,"confidence":0,"isHeader":false,"isFooter":false},{"rowIndex":3,"columnIndex":4,"elements":[],"boundingBox":[2.522,4.5765,2.7775,4.5765,2.7775,4.7548,2.522,4.7548],"text":"","rowSpan":0,"columnSpan":0,"confidence":0,"isHeader":false,"isFooter":false},{"rowIndex":3,"columnIndex":5,"elements":[],"boundingBox":[2.7775,4.5765,3.0329,4.5765,3.0329,4.7548,2.7775,4.7548],"text":"","rowSpan":0,"columnSpan":0,"confidence":0,"isHeader":false,"isFooter":false},{"rowIndex":3,"columnIndex":6,"elements":[],"boundingBox":[3.0329,4.5765,4.7057,4.5765,4.7057,4.7467,3.0329,4.7548],"text":"","rowSpan":0,"columnSpan":0,"confidence":0,"isHeader":false,"isFooter":false},{"rowIndex":3,"columnIndex":7,"elements":[],"boundingBox":[4.7057,4.5765,5.3567,4.5765,5.3567,4.7467,4.7057,4.7467],"text":"","rowSpan":0,"columnSpan":0,"confidence":0,"isHeader":false,"isFooter":false},{"rowIndex":3,"columnIndex":8,"elements":[],"boundingBox":[5.3567,4.5765,6.0076,4.5765,6.0076,4.7467,5.3567,4.7467],"text":"","rowSpan":0,"columnSpan":0,"confidence":0,"isHeader":false,"isFooter":false},{"rowIndex":3,"columnIndex":9,"elements":["#/readResults/0/lines/74/words/0","#/readResults/0/lines/74/words/1","#/readResults/0/lines/74/words/2","#/readResults/0/lines/74/words/3","#/readResults/0/lines/74/words/4"],"boundingBox":[6.0076,4.5765,7.2519,4.5765,7.2601,4.7467,6.0076,4.7467],"text":"MED EXP (Any one person)","rowSpan":0,"columnSpan":0,"confidence":0,"isHeader":false,"isFooter":false},{"rowIndex":3,"columnIndex":10,"elements":["#/readResults/0/lines/75/words/0","#/readResults/0/lines/75/words/1"],"boundingBox":[7.2519,4.5765,8.3478,4.5765,8.3478,4.7386,7.2601,4.7467],"text":"$ 5,000","rowSpan":0,"columnSpan":0,"confidence":0,"isHeader":false,"isFooter":false},{"rowIndex":4,"columnIndex":0,"elements":[],"boundingBox":[0.3054,4.7548,0.5526,4.7467,0.5526,4.9249,0.3137,4.9249],"text":"","rowSpan":0,"columnSpan":0,"confidence":0,"isHeader":false,"isFooter":false},{"rowIndex":4,"columnIndex":1,"elements":["#/readResults/0/selectionMarks/3"],"boundingBox":[0.5526,4.7467,0.7751,4.7467,0.7751,4.9249,0.5526,4.9249],"text":"","rowSpan":0,"columnSpan":0,"confidence":0,"isHeader":false,"isFooter":false},{"rowIndex":4,"columnIndex":2,"elements":[],"boundingBox":[0.7751,4.7467,2.522,4.7548,2.522,4.9249,0.7751,4.9249],"text":"","rowSpan":0,"columnSpan":2,"confidence":0,"isHeader":false,"isFooter":false},{"rowIndex":4,"columnIndex":4,"elements":[],"boundingBox":[2.522,4.7548,2.7775,4.7548,2.7775,4.9168,2.522,4.9249],"text":"","rowSpan":0,"columnSpan":0,"confidence":0,"isHeader":false,"isFooter":false},{"rowIndex":4,"columnIndex":5,"elements":[],"boundingBox":[2.7775,4.7548,3.0329,4.7548,3.0329,4.9168,2.7775,4.9168],"text":"","rowSpan":0,"columnSpan":0,"confidence":0,"isHeader":false,"isFooter":false},{"rowIndex":4,"columnIndex":6,"elements":[],"boundingBox":[3.0329,4.7548,4.7057,4.7467,4.6974,4.9168,3.0329,4.9168],"text":"","rowSpan":0,"columnSpan":0,"confidence":0,"isHeader":false,"isFooter":false},{"rowIndex":4,"columnIndex":7,"elements":[],"boundingBox":[4.7057,4.7467,5.3567,4.7467,5.3567,4.9168,4.6974,4.9168],"text":"","rowSpan":0,"columnSpan":0,"confidence":0,"isHeader":false,"isFooter":false},{"rowIndex":4,"columnIndex":8,"elements":[],"boundingBox":[5.3567,4.7467,6.0076,4.7467,6.0076,4.9168,5.3567,4.9168],"text":"","rowSpan":0,"columnSpan":0,"confidence":0,"isHeader":false,"isFooter":false},{"rowIndex":4,"columnIndex":9,"elements":["#/readResults/0/lines/76/words/0","#/readResults/0/lines/76/words/1","#/readResults/0/lines/76/words/2","#/readResults/0/lines/76/words/3"],"boundingBox":[6.0076,4.7467,7.2601,4.7467,7.2601,4.9168,6.0076,4.9168],"text":"PERSONAL & ADV INJURY","rowSpan":0,"columnSpan":0,"confidence":0,"isHeader":false,"isFooter":false},{"rowIndex":4,"columnIndex":10,"elements":["#/readResults/0/lines/77/words/0","#/readResults/0/lines/77/words/1"],"boundingBox":[7.2601,4.7467,8.3478,4.7386,8.3478,4.9087,7.2601,4.9168],"text":"$ 1,000,000","rowSpan":0,"columnSpan":0,"confidence":0,"isHeader":false,"isFooter":false},{"rowIndex":5,"columnIndex":0,"elements":[],"boundingBox":[0.3137,4.9249,0.5526,4.9249,0.5609,5.0789,0.3137,5.0789],"text":"","rowSpan":0,"columnSpan":0,"confidence":0,"isHeader":false,"isFooter":false},{"rowIndex":5,"columnIndex":1,"elements":["#/readResults/0/lines/78/words/0","#/readResults/0/lines/78/words/1","#/readResults/0/lines/78/words/2","#/readResults/0/lines/78/words/3","#/readResults/0/lines/78/words/4"],"boundingBox":[0.5526,4.9249,2.522,4.9249,2.5138,5.087,0.5609,5.0789],"text":"GEN'L AGGREGATE LIMIT APPLIES PER:","rowSpan":0,"columnSpan":3,"confidence":0,"isHeader":false,"isFooter":false},{"rowIndex":5,"columnIndex":4,"elements":[],"boundingBox":[2.522,4.9249,2.7775,4.9168,2.7775,5.087,2.5138,5.087],"text":"","rowSpan":0,"columnSpan":0,"confidence":0,"isHeader":false,"isFooter":false},{"rowIndex":5,"columnIndex":5,"elements":[],"boundingBox":[2.7775,4.9168,3.0329,4.9168,3.0329,5.087,2.7775,5.087],"text":"","rowSpan":0,"columnSpan":0,"confidence":0,"isHeader":false,"isFooter":false},{"rowIndex":5,"columnIndex":6,"elements":[],"boundingBox":[3.0329,4.9168,4.6974,4.9168,4.6974,5.087,3.0329,5.087],"text":"","rowSpan":0,"columnSpan":0,"confidence":0,"isHeader":false,"isFooter":false},{"rowIndex":5,"columnIndex":7,"elements":[],"boundingBox":[4.6974,4.9168,5.3567,4.9168,5.3567,5.087,4.6974,5.087],"text":"","rowSpan":0,"columnSpan":0,"confidence":0,"isHeader":false,"isFooter":false},{"rowIndex":5,"columnIndex":8,"elements":[],"boundingBox":[5.3567,4.9168,6.0076,4.9168,6.0076,5.0789,5.3567,5.087],"text":"","rowSpan":0,"columnSpan":0,"confidence":0,"isHeader":false,"isFooter":false},{"rowIndex":5,"columnIndex":9,"elements":["#/readResults/0/lines/79/words/0","#/readResults/0/lines/79/words/1"],"boundingBox":[6.0076,4.9168,7.2601,4.9168,7.2601,5.0789,6.0076,5.0789],"text":"GENERAL AGGREGATE","rowSpan":0,"columnSpan":0,"confidence":0,"isHeader":false,"isFooter":false},{"rowIndex":5,"columnIndex":10,"elements":["#/readResults/0/lines/80/words/0","#/readResults/0/lines/80/words/1"],"boundingBox":[7.2601,4.9168,8.3478,4.9087,8.3478,5.0789,7.2601,5.0789],"text":"$ 3,000,000","rowSpan":0,"columnSpan":0,"confidence":0,"isHeader":false,"isFooter":false},{"rowIndex":6,"columnIndex":0,"elements":[],"boundingBox":[0.3137,5.0789,0.5609,5.0789,0.5609,5.2653,0.3137,5.2653],"text":"","rowSpan":0,"columnSpan":0,"confidence":0,"isHeader":false,"isFooter":false},{"rowIndex":6,"columnIndex":1,"elements":["#/readResults/0/selectionMarks/4"],"boundingBox":[0.5609,5.0789,0.7751,5.0789,0.7751,5.2653,0.5609,5.2653],"text":"","rowSpan":0,"columnSpan":0,"confidence":0,"isHeader":false,"isFooter":false},{"rowIndex":6,"columnIndex":2,"elements":["#/readResults/0/lines/81/words/0","#/readResults/0/lines/82/words/0","#/readResults/0/lines/83/words/0","#/readResults/0/lines/84/words/0","#/readResults/0/lines/85/words/0","#/readResults/0/selectionMarks/5","#/readResults/0/selectionMarks/6"],"boundingBox":[0.7751,5.0789,2.5138,5.087,2.5138,5.2572,0.7751,5.2653],"text":"PRO- X POLICY JECT LOC","rowSpan":0,"columnSpan":2,"confidence":0,"isHeader":false,"isFooter":false},{"rowIndex":6,"columnIndex":4,"elements":[],"boundingBox":[2.5138,5.087,2.7775,5.087,2.7775,5.2572,2.5138,5.2572],"text":"","rowSpan":0,"columnSpan":0,"confidence":0,"isHeader":false,"isFooter":false},{"rowIndex":6,"columnIndex":5,"elements":[],"boundingBox":[2.7775,5.087,3.0329,5.087,3.0329,5.2491,2.7775,5.2572],"text":"","rowSpan":0,"columnSpan":0,"confidence":0,"isHeader":false,"isFooter":false},{"rowIndex":6,"columnIndex":6,"elements":[],"boundingBox":[3.0329,5.087,4.6974,5.087,4.6974,5.2491,3.0329,5.2491],"text":"","rowSpan":0,"columnSpan":0,"confidence":0,"isHeader":false,"isFooter":false},{"rowIndex":6,"columnIndex":7,"elements":[],"boundingBox":[4.6974,5.087,5.3567,5.087,5.3567,5.241,4.6974,5.2491],"text":"","rowSpan":0,"columnSpan":0,"confidence":0,"isHeader":false,"isFooter":false},{"rowIndex":6,"columnIndex":8,"elements":[],"boundingBox":[5.3567,5.087,6.0076,5.0789,6.0076,5.241,5.3567,5.241],"text":"","rowSpan":0,"columnSpan":0,"confidence":0,"isHeader":false,"isFooter":false},{"rowIndex":6,"columnIndex":9,"elements":["#/readResults/0/lines/86/words/0","#/readResults/0/lines/86/words/1","#/readResults/0/lines/86/words/2","#/readResults/0/lines/86/words/3"],"boundingBox":[6.0076,5.0789,7.2601,5.0789,7.2601,5.2491,6.0076,5.241],"text":"PRODUCTS - COMP/OP AGG","rowSpan":0,"columnSpan":0,"confidence":0,"isHeader":false,"isFooter":false},{"rowIndex":6,"columnIndex":10,"elements":["#/readResults/0/lines/87/words/0","#/readResults/0/lines/87/words/1"],"boundingBox":[7.2601,5.0789,8.3478,5.0789,8.3478,5.241,7.2601,5.2491],"text":"$ 3,000,000","rowSpan":0,"columnSpan":0,"confidence":0,"isHeader":false,"isFooter":false},{"rowIndex":7,"columnIndex":0,"elements":[],"boundingBox":[0.3137,5.2653,0.5609,5.2653,0.5609,5.403,0.3137,5.403],"text":"","rowSpan":0,"columnSpan":0,"confidence":0,"isHeader":false,"isFooter":false},{"rowIndex":7,"columnIndex":1,"elements":["#/readResults/0/selectionMarks/7"],"boundingBox":[0.5609,5.2653,0.7751,5.2653,0.7751,5.403,0.5609,5.403],"text":"","rowSpan":0,"columnSpan":0,"confidence":0,"isHeader":false,"isFooter":false},{"rowIndex":7,"columnIndex":2,"elements":["#/readResults/0/lines/88/words/0"],"boundingBox":[0.7751,5.2653,1.6074,5.2572,1.6074,5.403,0.7751,5.403],"text":"OTHER:","rowSpan":0,"columnSpan":0,"confidence":0,"isHeader":false,"isFooter":false},{"rowIndex":7,"columnIndex":3,"elements":[],"boundingBox":[1.6074,5.2572,2.5138,5.2572,2.5138,5.3949,1.6074,5.403],"text":"","rowSpan":0,"columnSpan":0,"confidence":0,"isHeader":false,"isFooter":false},{"rowIndex":7,"columnIndex":4,"elements":[],"boundingBox":[2.5138,5.2572,2.7775,5.2572,2.7775,5.3949,2.5138,5.3949],"text":"","rowSpan":0,"columnSpan":0,"confidence":0,"isHeader":false,"isFooter":false},{"rowIndex":7,"columnIndex":5,"elements":[],"boundingBox":[2.7775,5.2572,3.0329,5.2491,3.0329,5.3949,2.7775,5.3949],"text":"","rowSpan":0,"columnSpan":0,"confidence":0,"isHeader":false,"isFooter":false},{"rowIndex":7,"columnIndex":6,"elements":[],"boundingBox":[3.0329,5.2491,4.6974,5.2491,4.6974,5.3949,3.0329,5.3949],"text":"","rowSpan":0,"columnSpan":0,"confidence":0,"isHeader":false,"isFooter":false},{"rowIndex":7,"columnIndex":7,"elements":[],"boundingBox":[4.6974,5.2491,5.3567,5.241,5.3567,5.3949,4.6974,5.3949],"text":"","rowSpan":0,"columnSpan":0,"confidence":0,"isHeader":false,"isFooter":false},{"rowIndex":7,"columnIndex":8,"elements":[],"boundingBox":[5.3567,5.241,6.0076,5.241,6.0076,5.3949,5.3567,5.3949],"text":"","rowSpan":0,"columnSpan":0,"confidence":0,"isHeader":false,"isFooter":false},{"rowIndex":7,"columnIndex":9,"elements":[],"boundingBox":[6.0076,5.241,7.2601,5.2491,7.2601,5.3868,6.0076,5.3949],"text":"","rowSpan":0,"columnSpan":0,"confidence":0,"isHeader":false,"isFooter":false},{"rowIndex":7,"columnIndex":10,"elements":["#/readResults/0/lines/89/words/0"],"boundingBox":[7.2601,5.2491,8.3478,5.241,8.3478,5.3868,7.2601,5.3868],"text":"$","rowSpan":0,"columnSpan":0,"confidence":0,"isHeader":false,"isFooter":false},{"rowIndex":8,"columnIndex":0,"elements":["#/readResults/0/lines/90/words/0"],"boundingBox":[0.3137,5.403,0.5609,5.403,0.5609,5.7353,0.3137,5.7353],"text":"B","rowSpan":2,"columnSpan":0,"confidence":0,"isHeader":false,"isFooter":false},{"rowIndex":8,"columnIndex":1,"elements":["#/readResults/0/lines/91/words/0","#/readResults/0/lines/91/words/1"],"boundingBox":[0.5609,5.403,1.6074,5.403,1.6074,5.5732,0.5609,5.5732],"text":"AUTOMOBILE LIABILITY","rowSpan":0,"columnSpan":2,"confidence":0,"isHeader":false,"isFooter":false},{"rowIndex":8,"columnIndex":3,"elements":[],"boundingBox":[1.6074,5.403,2.5138,5.3949,2.5138,5.5732,1.6074,5.5732],"text":"","rowSpan":0,"columnSpan":0,"confidence":0,"isHeader":false,"isFooter":false},{"rowIndex":8,"columnIndex":4,"elements":[],"boundingBox":[2.5138,5.3949,2.7775,5.3949,2.7775,5.5732,2.5138,5.5732],"text":"","rowSpan":0,"columnSpan":0,"confidence":0,"isHeader":false,"isFooter":false},{"rowIndex":8,"columnIndex":5,"elements":[],"boundingBox":[2.7775,5.3949,3.0329,5.3949,3.0329,5.5732,2.7775,5.5732],"text":"","rowSpan":0,"columnSpan":0,"confidence":0,"isHeader":false,"isFooter":false},{"rowIndex":8,"columnIndex":6,"elements":["#/readResults/0/lines/92/words/0"],"boundingBox":[3.0329,5.3949,4.6974,5.3949,4.6974,5.5732,3.0329,5.5732],"text":"CAP3142096","rowSpan":0,"columnSpan":0,"confidence":0,"isHeader":false,"isFooter":false},{"rowIndex":8,"columnIndex":7,"elements":["#/readResults/0/lines/93/words/0"],"boundingBox":[4.6974,5.3949,5.3567,5.3949,5.3567,5.5732,4.6974,5.5732],"text":"6/1/2021","rowSpan":0,"columnSpan":0,"confidence":0,"isHeader":false,"isFooter":false},{"rowIndex":8,"columnIndex":8,"elements":["#/readResults/0/lines/94/words/0"],"boundingBox":[5.3567,5.3949,6.0076,5.3949,6.0076,5.5732,5.3567,5.5732],"text":"6/1/2022","rowSpan":0,"columnSpan":0,"confidence":0,"isHeader":false,"isFooter":false},{"rowIndex":8,"columnIndex":9,"elements":["#/readResults/0/lines/95/words/0","#/readResults/0/lines/95/words/1","#/readResults/0/lines/95/words/2","#/readResults/0/lines/96/words/0","#/readResults/0/lines/96/words/1"],"boundingBox":[6.0076,5.3949,7.2601,5.3868,7.2601,5.5732,6.0076,5.5732],"text":"COMBINED SINGLE LIMIT (Ea accident).","rowSpan":0,"columnSpan":0,"confidence":0,"isHeader":false,"isFooter":false},{"rowIndex":8,"columnIndex":10,"elements":["#/readResults/0/lines/97/words/0","#/readResults/0/lines/97/words/1"],"boundingBox":[7.2601,5.3868,8.3478,5.3868,8.3478,5.5732,7.2601,5.5732],"text":"$ 1,000,000","rowSpan":0,"columnSpan":0,"confidence":0,"isHeader":false,"isFooter":false},{"rowIndex":9,"columnIndex":1,"elements":["#/readResults/0/lines/98/words/0","#/readResults/0/selectionMarks/8"],"boundingBox":[0.5609,5.5732,0.7669,5.5651,0.7669,5.7272,0.5609,5.7353],"text":"X","rowSpan":0,"columnSpan":0,"confidence":0,"isHeader":false,"isFooter":false},{"rowIndex":9,"columnIndex":2,"elements":["#/readResults/0/lines/99/words/0","#/readResults/0/lines/99/words/1"],"boundingBox":[0.7669,5.5651,1.6074,5.5732,1.5991,5.7272,0.7669,5.7272],"text":"ANY AUTO","rowSpan":0,"columnSpan":0,"confidence":0,"isHeader":false,"isFooter":false},{"rowIndex":9,"columnIndex":3,"elements":[],"boundingBox":[1.6074,5.5732,2.5138,5.5732,2.5138,5.7272,1.5991,5.7272],"text":"","rowSpan":0,"columnSpan":0,"confidence":0,"isHeader":false,"isFooter":false},{"rowIndex":9,"columnIndex":4,"elements":[],"boundingBox":[2.5138,5.5732,2.7775,5.5732,2.7775,5.7272,2.5138,5.7272],"text":"","rowSpan":0,"columnSpan":0,"confidence":0,"isHeader":false,"isFooter":false},{"rowIndex":9,"columnIndex":5,"elements":[],"boundingBox":[2.7775,5.5732,3.0329,5.5732,3.0329,5.7272,2.7775,5.7272],"text":"","rowSpan":0,"columnSpan":0,"confidence":0,"isHeader":false,"isFooter":false},{"rowIndex":9,"columnIndex":6,"elements":[],"boundingBox":[3.0329,5.5732,4.6974,5.5732,4.6974,5.7272,3.0329,5.7272],"text":"","rowSpan":0,"columnSpan":0,"confidence":0,"isHeader":false,"isFooter":false},{"rowIndex":9,"columnIndex":7,"elements":[],"boundingBox":[4.6974,5.5732,5.3567,5.5732,5.3567,5.7272,4.6974,5.7272],"text":"","rowSpan":0,"columnSpan":0,"confidence":0,"isHeader":false,"isFooter":false},{"rowIndex":9,"columnIndex":8,"elements":[],"boundingBox":[5.3567,5.5732,6.0076,5.5732,6.0076,5.7272,5.3567,5.7272],"text":"","rowSpan":0,"columnSpan":0,"confidence":0,"isHeader":false,"isFooter":false},{"rowIndex":9,"columnIndex":9,"elements":["#/readResults/0/lines/100/words/0","#/readResults/0/lines/100/words/1","#/readResults/0/lines/100/words/2","#/readResults/0/lines/100/words/3"],"boundingBox":[6.0076,5.5732,7.2601,5.5732,7.2601,5.7272,6.0076,5.7272],"text":"BODILY INJURY (Per person)","rowSpan":0,"columnSpan":0,"confidence":0,"isHeader":false,"isFooter":false},{"rowIndex":9,"columnIndex":10,"elements":["#/readResults/0/lines/101/words/0"],"boundingBox":[7.2601,5.5732,8.3478,5.5732,8.3478,5.7272,7.2601,5.7272],"text":"$","rowSpan":0,"columnSpan":0,"confidence":0,"isHeader":false,"isFooter":false},{"rowIndex":10,"columnIndex":0,"elements":[],"boundingBox":[0.3137,5.7353,0.5609,5.7353,0.5609,6.2377,0.3137,6.2458],"text":"","rowSpan":3,"columnSpan":0,"confidence":0,"isHeader":false,"isFooter":false},{"rowIndex":10,"columnIndex":1,"elements":["#/readResults/0/selectionMarks/9"],"boundingBox":[0.5609,5.7353,0.7669,5.7272,0.7669,5.9135,0.5609,5.9135],"text":"","rowSpan":0,"columnSpan":0,"confidence":0,"isHeader":false,"isFooter":false},{"rowIndex":10,"columnIndex":2,"elements":["#/readResults/0/lines/102/words/0","#/readResults/0/lines/104/words/0","#/readResults/0/lines/104/words/1"],"boundingBox":[0.7669,5.7272,1.5991,5.7272,1.5991,5.9054,0.7669,5.9135],"text":"OWNED AUTOS ONLY","rowSpan":0,"columnSpan":0,"confidence":0,"isHeader":false,"isFooter":false},{"rowIndex":10,"columnIndex":3,"elements":["#/readResults/0/lines/103/words/0","#/readResults/0/lines/105/words/0","#/readResults/0/selectionMarks/10"],"boundingBox":[1.5991,5.7272,2.5138,5.7272,2.5138,5.8973,1.5991,5.9054],"text":"SCHEDULED AUTOS","rowSpan":0,"columnSpan":0,"confidence":0,"isHeader":false,"isFooter":false},{"rowIndex":10,"columnIndex":4,"elements":[],"boundingBox":[2.5138,5.7272,2.7775,5.7272,2.7775,5.8973,2.5138,5.8973],"text":"","rowSpan":0,"columnSpan":0,"confidence":0,"isHeader":false,"isFooter":false},{"rowIndex":10,"columnIndex":5,"elements":[],"boundingBox":[2.7775,5.7272,3.0329,5.7272,3.0329,5.8973,2.7775,5.8973],"text":"","rowSpan":0,"columnSpan":0,"confidence":0,"isHeader":false,"isFooter":false},{"rowIndex":10,"columnIndex":6,"elements":[],"boundingBox":[3.0329,5.7272,4.6974,5.7272,4.6974,5.8892,3.0329,5.8973],"text":"","rowSpan":0,"columnSpan":0,"confidence":0,"isHeader":false,"isFooter":false},{"rowIndex":10,"columnIndex":7,"elements":[],"boundingBox":[4.6974,5.7272,5.3567,5.7272,5.3567,5.8811,4.6974,5.8892],"text":"","rowSpan":0,"columnSpan":0,"confidence":0,"isHeader":false,"isFooter":false},{"rowIndex":10,"columnIndex":8,"elements":[],"boundingBox":[5.3567,5.7272,6.0076,5.7272,6.0076,5.8811,5.3567,5.8811],"text":"","rowSpan":0,"columnSpan":0,"confidence":0,"isHeader":false,"isFooter":false},{"rowIndex":10,"columnIndex":9,"elements":["#/readResults/0/lines/106/words/0","#/readResults/0/lines/106/words/1","#/readResults/0/lines/106/words/2","#/readResults/0/lines/106/words/3"],"boundingBox":[6.0076,5.7272,7.2601,5.7272,7.2601,5.8811,6.0076,5.8811],"text":"BODILY INJURY (Per accident)","rowSpan":0,"columnSpan":0,"confidence":0,"isHeader":false,"isFooter":false},{"rowIndex":10,"columnIndex":10,"elements":["#/readResults/0/lines/107/words/0"],"boundingBox":[7.2601,5.7272,8.3478,5.7272,8.3478,5.8811,7.2601,5.8811],"text":"$","rowSpan":0,"columnSpan":0,"confidence":0,"isHeader":false,"isFooter":false},{"rowIndex":11,"columnIndex":1,"elements":["#/readResults/0/selectionMarks/11"],"boundingBox":[0.5609,5.9135,0.7669,5.9135,0.7669,6.0918,0.5609,6.0918],"text":"","rowSpan":0,"columnSpan":0,"confidence":0,"isHeader":false,"isFooter":false},{"rowIndex":11,"columnIndex":2,"elements":["#/readResults/0/lines/108/words/0","#/readResults/0/lines/111/words/0","#/readResults/0/lines/111/words/1"],"boundingBox":[0.7669,5.9135,1.5991,5.9054,1.5991,6.0918,0.7669,6.0918],"text":"HIRED AUTOS ONLY","rowSpan":0,"columnSpan":0,"confidence":0,"isHeader":false,"isFooter":false},{"rowIndex":11,"columnIndex":3,"elements":["#/readResults/0/lines/109/words/0","#/readResults/0/lines/112/words/0","#/readResults/0/lines/112/words/1"],"boundingBox":[1.5991,5.9054,2.5138,5.8973,2.5138,6.0918,1.5991,6.0918],"text":"NON-OWNED AUTOS ONLY","rowSpan":0,"columnSpan":0,"confidence":0,"isHeader":false,"isFooter":false},{"rowIndex":11,"columnIndex":4,"elements":[],"boundingBox":[2.5138,5.8973,2.7775,5.8973,2.7775,6.0918,2.5138,6.0918],"text":"","rowSpan":0,"columnSpan":0,"confidence":0,"isHeader":false,"isFooter":false},{"rowIndex":11,"columnIndex":5,"elements":[],"boundingBox":[2.7775,5.8973,3.0329,5.8973,3.0329,6.0918,2.7775,6.0918],"text":"","rowSpan":0,"columnSpan":0,"confidence":0,"isHeader":false,"isFooter":false},{"rowIndex":11,"columnIndex":6,"elements":[],"boundingBox":[3.0329,5.8973,4.6974,5.8892,4.6974,6.0837,3.0329,6.0918],"text":"","rowSpan":0,"columnSpan":0,"confidence":0,"isHeader":false,"isFooter":false},{"rowIndex":11,"columnIndex":7,"elements":[],"boundingBox":[4.6974,5.8892,5.3567,5.8811,5.3567,6.0756,4.6974,6.0837],"text":"","rowSpan":0,"columnSpan":0,"confidence":0,"isHeader":false,"isFooter":false},{"rowIndex":11,"columnIndex":8,"elements":[],"boundingBox":[5.3567,5.8811,6.0076,5.8811,6.0076,6.0756,5.3567,6.0756],"text":"","rowSpan":0,"columnSpan":0,"confidence":0,"isHeader":false,"isFooter":false},{"rowIndex":11,"columnIndex":9,"elements":["#/readResults/0/lines/110/words/0","#/readResults/0/lines/110/words/1","#/readResults/0/lines/113/words/0","#/readResults/0/lines/113/words/1"],"boundingBox":[6.0076,5.8811,7.2601,5.8811,7.2601,6.0756,6.0076,6.0756],"text":"PROPERTY DAMAGE (Per accident)","rowSpan":0,"columnSpan":0,"confidence":0,"isHeader":false,"isFooter":false},{"rowIndex":11,"columnIndex":10,"elements":["#/readResults/0/lines/114/words/0"],"boundingBox":[7.2601,5.8811,8.3478,5.8811,8.3478,6.0756,7.2601,6.0756],"text":"$","rowSpan":0,"columnSpan":0,"confidence":0,"isHeader":false,"isFooter":false},{"rowIndex":12,"columnIndex":1,"elements":[],"boundingBox":[0.5609,6.0918,0.7669,6.0918,0.7669,6.2377,0.5609,6.2377],"text":"","rowSpan":0,"columnSpan":0,"confidence":0,"isHeader":false,"isFooter":false},{"rowIndex":12,"columnIndex":2,"elements":[],"boundingBox":[0.7669,6.0918,1.5991,6.0918,1.5991,6.2377,0.7669,6.2377],"text":"","rowSpan":0,"columnSpan":0,"confidence":0,"isHeader":false,"isFooter":false},{"rowIndex":12,"columnIndex":3,"elements":[],"boundingBox":[1.5991,6.0918,2.5138,6.0918,2.5138,6.2377,1.5991,6.2377],"text":"","rowSpan":0,"columnSpan":0,"confidence":0,"isHeader":false,"isFooter":false},{"rowIndex":12,"columnIndex":4,"elements":[],"boundingBox":[2.5138,6.0918,2.7775,6.0918,2.7775,6.2377,2.5138,6.2377],"text":"","rowSpan":0,"columnSpan":0,"confidence":0,"isHeader":false,"isFooter":false},{"rowIndex":12,"columnIndex":5,"elements":[],"boundingBox":[2.7775,6.0918,3.0329,6.0918,3.0329,6.2296,2.7775,6.2377],"text":"","rowSpan":0,"columnSpan":0,"confidence":0,"isHeader":false,"isFooter":false},{"rowIndex":12,"columnIndex":6,"elements":[],"boundingBox":[3.0329,6.0918,4.6974,6.0837,4.6974,6.2296,3.0329,6.2296],"text":"","rowSpan":0,"columnSpan":0,"confidence":0,"isHeader":false,"isFooter":false},{"rowIndex":12,"columnIndex":7,"elements":[],"boundingBox":[4.6974,6.0837,5.3567,6.0756,5.3567,6.2296,4.6974,6.2296],"text":"","rowSpan":0,"columnSpan":0,"confidence":0,"isHeader":false,"isFooter":false},{"rowIndex":12,"columnIndex":8,"elements":[],"boundingBox":[5.3567,6.0756,6.0076,6.0756,6.0076,6.2215,5.3567,6.2296],"text":"","rowSpan":0,"columnSpan":0,"confidence":0,"isHeader":false,"isFooter":false},{"rowIndex":12,"columnIndex":9,"elements":[],"boundingBox":[6.0076,6.0756,7.2601,6.0756,7.2601,6.2215,6.0076,6.2215],"text":"","rowSpan":0,"columnSpan":0,"confidence":0,"isHeader":false,"isFooter":false},{"rowIndex":12,"columnIndex":10,"elements":["#/readResults/0/lines/115/words/0"],"boundingBox":[7.2601,6.0756,8.3478,6.0756,8.3478,6.2215,7.2601,6.2215],"text":"$","rowSpan":0,"columnSpan":0,"confidence":0,"isHeader":false,"isFooter":false},{"rowIndex":13,"columnIndex":0,"elements":["#/readResults/0/lines/117/words/0"],"boundingBox":[0.3137,6.2458,0.5609,6.2377,0.5691,6.416,0.3137,6.416],"text":"B","rowSpan":0,"columnSpan":0,"confidence":0,"isHeader":false,"isFooter":false},{"rowIndex":13,"columnIndex":1,"elements":["#/readResults/0/lines/123/words/0"],"boundingBox":[0.5609,6.2377,0.7669,6.2377,0.7669,6.416,0.5691,6.416],"text":"X","rowSpan":0,"columnSpan":0,"confidence":0,"isHeader":false,"isFooter":false},{"rowIndex":13,"columnIndex":2,"elements":["#/readResults/0/lines/118/words/0","#/readResults/0/lines/118/words/1"],"boundingBox":[0.7669,6.2377,1.5991,6.2377,1.5991,6.416,0.7669,6.416],"text":"UMBRELLA LIAB","rowSpan":0,"columnSpan":0,"confidence":0,"isHeader":false,"isFooter":false},{"rowIndex":13,"columnIndex":3,"elements":["#/readResults/0/lines/116/words/0","#/readResults/0/lines/119/words/0","#/readResults/0/selectionMarks/13"],"boundingBox":[1.5991,6.2377,2.5138,6.2377,2.5138,6.416,1.5991,6.416],"text":"X OCCUR","rowSpan":0,"columnSpan":0,"confidence":0,"isHeader":false,"isFooter":false},{"rowIndex":13,"columnIndex":4,"elements":[],"boundingBox":[2.5138,6.2377,2.7775,6.2377,2.7775,6.416,2.5138,6.416],"text":"","rowSpan":0,"columnSpan":0,"confidence":0,"isHeader":false,"isFooter":false},{"rowIndex":13,"columnIndex":5,"elements":[],"boundingBox":[2.7775,6.2377,3.0329,6.2296,3.0329,6.416,2.7775,6.416],"text":"","rowSpan":0,"columnSpan":0,"confidence":0,"isHeader":false,"isFooter":false},{"rowIndex":13,"columnIndex":6,"elements":["#/readResults/0/lines/120/words/0"],"boundingBox":[3.0329,6.2296,4.6974,6.2296,4.6974,6.416,3.0329,6.416],"text":"UMB3142097","rowSpan":0,"columnSpan":0,"confidence":0,"isHeader":false,"isFooter":false},{"rowIndex":13,"columnIndex":7,"elements":["#/readResults/0/lines/121/words/0"],"boundingBox":[4.6974,6.2296,5.3567,6.2296,5.3567,6.416,4.6974,6.416],"text":"6/1/2021","rowSpan":0,"columnSpan":0,"confidence":0,"isHeader":false,"isFooter":false},{"rowIndex":13,"columnIndex":8,"elements":["#/readResults/0/lines/122/words/0"],"boundingBox":[5.3567,6.2296,6.0076,6.2215,6.0076,6.416,5.3567,6.416],"text":"6/1/2022","rowSpan":0,"columnSpan":0,"confidence":0,"isHeader":false,"isFooter":false},{"rowIndex":13,"columnIndex":9,"elements":["#/readResults/0/lines/124/words/0","#/readResults/0/lines/124/words/1"],"boundingBox":[6.0076,6.2215,7.2601,6.2215,7.2601,6.416,6.0076,6.416],"text":"EACH OCCURRENCE","rowSpan":0,"columnSpan":0,"confidence":0,"isHeader":false,"isFooter":false},{"rowIndex":13,"columnIndex":10,"elements":["#/readResults/0/lines/125/words/0","#/readResults/0/lines/125/words/1"],"boundingBox":[7.2601,6.2215,8.3478,6.2215,8.3478,6.4078,7.2601,6.416],"text":"$ 10,000,000","rowSpan":0,"columnSpan":0,"confidence":0,"isHeader":false,"isFooter":false},{"rowIndex":14,"columnIndex":0,"elements":[],"boundingBox":[0.3137,6.416,0.5691,6.416,0.5691,6.7401,0.3137,6.7482],"text":"","rowSpan":2,"columnSpan":0,"confidence":0,"isHeader":false,"isFooter":false},{"rowIndex":14,"columnIndex":1,"elements":["#/readResults/0/selectionMarks/12"],"boundingBox":[0.5691,6.416,0.7669,6.416,0.7669,6.6023,0.5691,6.6023],"text":"","rowSpan":0,"columnSpan":0,"confidence":0,"isHeader":false,"isFooter":false},{"rowIndex":14,"columnIndex":2,"elements":["#/readResults/0/lines/126/words/0","#/readResults/0/lines/126/words/1"],"boundingBox":[0.7669,6.416,1.5991,6.416,1.5909,6.6023,0.7669,6.6023],"text":"EXCESS LIAB","rowSpan":0,"columnSpan":0,"confidence":0,"isHeader":false,"isFooter":false},{"rowIndex":14,"columnIndex":3,"elements":["#/readResults/0/lines/127/words/0","#/readResults/0/selectionMarks/14"],"boundingBox":[1.5991,6.416,2.5138,6.416,2.5138,6.6023,1.5909,6.6023],"text":"CLAIMS-MADE","rowSpan":0,"columnSpan":0,"confidence":0,"isHeader":false,"isFooter":false},{"rowIndex":14,"columnIndex":4,"elements":[],"boundingBox":[2.5138,6.416,2.7775,6.416,2.7775,6.6023,2.5138,6.6023],"text":"","rowSpan":0,"columnSpan":0,"confidence":0,"isHeader":false,"isFooter":false},{"rowIndex":14,"columnIndex":5,"elements":[],"boundingBox":[2.7775,6.416,3.0329,6.416,3.0329,6.6023,2.7775,6.6023],"text":"","rowSpan":0,"columnSpan":0,"confidence":0,"isHeader":false,"isFooter":false},{"rowIndex":14,"columnIndex":6,"elements":[],"boundingBox":[3.0329,6.416,4.6974,6.416,4.6974,6.5942,3.0329,6.6023],"text":"","rowSpan":0,"columnSpan":0,"confidence":0,"isHeader":false,"isFooter":false},{"rowIndex":14,"columnIndex":7,"elements":[],"boundingBox":[4.6974,6.416,5.3567,6.416,5.3567,6.5861,4.6974,6.5942],"text":"","rowSpan":0,"columnSpan":0,"confidence":0,"isHeader":false,"isFooter":false},{"rowIndex":14,"columnIndex":8,"elements":[],"boundingBox":[5.3567,6.416,6.0076,6.416,6.0076,6.5861,5.3567,6.5861],"text":"","rowSpan":0,"columnSpan":0,"confidence":0,"isHeader":false,"isFooter":false},{"rowIndex":14,"columnIndex":9,"elements":["#/readResults/0/lines/128/words/0"],"boundingBox":[6.0076,6.416,7.2601,6.416,7.2684,6.5861,6.0076,6.5861],"text":"AGGREGATE","rowSpan":0,"columnSpan":0,"confidence":0,"isHeader":false,"isFooter":false},{"rowIndex":14,"columnIndex":10,"elements":["#/readResults/0/lines/129/words/0","#/readResults/0/lines/129/words/1"],"boundingBox":[7.2601,6.416,8.3478,6.4078,8.3478,6.5861,7.2684,6.5861],"text":"$ 10,000,000","rowSpan":0,"columnSpan":0,"confidence":0,"isHeader":false,"isFooter":false},{"rowIndex":15,"columnIndex":1,"elements":[],"boundingBox":[0.5691,6.6023,0.7669,6.6023,0.7669,6.7401,0.5691,6.7401],"text":"","rowSpan":0,"columnSpan":0,"confidence":0,"isHeader":false,"isFooter":false},{"rowIndex":15,"columnIndex":2,"elements":["#/readResults/0/lines/130/words/0","#/readResults/0/lines/131/words/0","#/readResults/0/lines/131/words/1"],"boundingBox":[0.7669,6.6023,2.5138,6.6023,2.5138,6.732,0.7669,6.7401],"text":"DED RETENTION $","rowSpan":0,"columnSpan":2,"confidence":0,"isHeader":false,"isFooter":false},{"rowIndex":15,"columnIndex":4,"elements":[],"boundingBox":[2.5138,6.6023,2.7775,6.6023,2.7775,6.732,2.5138,6.732],"text":"","rowSpan":0,"columnSpan":0,"confidence":0,"isHeader":false,"isFooter":false},{"rowIndex":15,"columnIndex":5,"elements":[],"boundingBox":[2.7775,6.6023,3.0329,6.6023,3.0329,6.732,2.7775,6.732],"text":"","rowSpan":0,"columnSpan":0,"confidence":0,"isHeader":false,"isFooter":false},{"rowIndex":15,"columnIndex":6,"elements":[],"boundingBox":[3.0329,6.6023,4.6974,6.5942,4.6974,6.7239,3.0329,6.732],"text":"","rowSpan":0,"columnSpan":0,"confidence":0,"isHeader":false,"isFooter":false},{"rowIndex":15,"columnIndex":7,"elements":[],"boundingBox":[4.6974,6.5942,5.3567,6.5861,5.3567,6.7239,4.6974,6.7239],"text":"","rowSpan":0,"columnSpan":0,"confidence":0,"isHeader":false,"isFooter":false},{"rowIndex":15,"columnIndex":8,"elements":[],"boundingBox":[5.3567,6.5861,6.0076,6.5861,6.0076,6.7239,5.3567,6.7239],"text":"","rowSpan":0,"columnSpan":0,"confidence":0,"isHeader":false,"isFooter":false},{"rowIndex":15,"columnIndex":9,"elements":[],"boundingBox":[6.0076,6.5861,7.2684,6.5861,7.2684,6.7239,6.0076,6.7239],"text":"","rowSpan":0,"columnSpan":0,"confidence":0,"isHeader":false,"isFooter":false},{"rowIndex":15,"columnIndex":10,"elements":["#/readResults/0/lines/132/words/0"],"boundingBox":[7.2684,6.5861,8.3478,6.5861,8.3478,6.7239,7.2684,6.7239],"text":"$","rowSpan":0,"columnSpan":0,"confidence":0,"isHeader":false,"isFooter":false},{"rowIndex":16,"columnIndex":0,"elements":["#/readResults/0/lines/133/words/0"],"boundingBox":[0.3137,6.7482,0.5691,6.7401,0.5691,7.1371,0.3137,7.1371],"text":"D","rowSpan":2,"columnSpan":0,"confidence":0,"isHeader":false,"isFooter":false},{"rowIndex":16,"columnIndex":1,"elements":["#/readResults/0/lines/134/words/0","#/readResults/0/lines/134/words/1","#/readResults/0/lines/141/words/0","#/readResults/0/lines/141/words/1","#/readResults/0/lines/141/words/2","#/readResults/0/lines/144/words/0","#/readResults/0/lines/144/words/1","#/readResults/0/lines/144/words/2"],"boundingBox":[0.5691,6.7401,2.5138,6.732,2.5138,6.967,0.5691,6.9589],"text":"WORKERS COMPENSATION AND EMPLOYERS' LIABILITY Y / N","rowSpan":0,"columnSpan":3,"confidence":0,"isHeader":false,"isFooter":false},{"rowIndex":16,"columnIndex":4,"elements":[],"boundingBox":[2.5138,6.732,2.7775,6.732,2.7775,6.967,2.5138,6.967],"text":"","rowSpan":0,"columnSpan":0,"confidence":0,"isHeader":false,"isFooter":false},{"rowIndex":16,"columnIndex":5,"elements":[],"boundingBox":[2.7775,6.732,3.0329,6.732,3.0329,6.9589,2.7775,6.967],"text":"","rowSpan":0,"columnSpan":0,"confidence":0,"isHeader":false,"isFooter":false},{"rowIndex":16,"columnIndex":6,"elements":["#/readResults/0/lines/135/words/0"],"boundingBox":[3.0329,6.732,4.6974,6.7239,4.6974,6.9102,3.0329,6.9589],"text":"2000034019","rowSpan":0,"columnSpan":0,"confidence":0,"isHeader":false,"isFooter":false},{"rowIndex":16,"columnIndex":7,"elements":["#/readResults/0/lines/136/words/0"],"boundingBox":[4.6974,6.7239,5.3567,6.7239,5.3567,6.9021,4.6974,6.9102],"text":"6/1/2021","rowSpan":0,"columnSpan":0,"confidence":0,"isHeader":false,"isFooter":false},{"rowIndex":16,"columnIndex":8,"elements":["#/readResults/0/lines/137/words/0"],"boundingBox":[5.3567,6.7239,6.0076,6.7239,6.0076,6.9021,5.3567,6.9021],"text":"6/1/2022","rowSpan":0,"columnSpan":0,"confidence":0,"isHeader":false,"isFooter":false},{"rowIndex":16,"columnIndex":9,"elements":["#/readResults/0/lines/138/words/0","#/readResults/0/lines/139/words/0","#/readResults/0/lines/140/words/0","#/readResults/0/lines/142/words/0","#/readResults/0/lines/143/words/0"],"boundingBox":[6.0076,6.7239,7.2684,6.7239,7.2684,6.9021,6.0076,6.9021],"text":"PER STATUTE OTH- ER X","rowSpan":0,"columnSpan":0,"confidence":0,"isHeader":false,"isFooter":false},{"rowIndex":16,"columnIndex":10,"elements":[],"boundingBox":[7.2684,6.7239,8.3478,6.7239,8.3478,6.894,7.2684,6.9021],"text":"","rowSpan":0,"columnSpan":0,"confidence":0,"isHeader":false,"isFooter":false},{"rowIndex":17,"columnIndex":1,"elements":["#/readResults/0/lines/145/words/0","#/readResults/0/lines/146/words/0","#/readResults/0/selectionMarks/15"],"boundingBox":[0.5691,6.9589,2.5138,6.967,2.5056,7.129,0.5691,7.1371],"text":"ANYPROPRIETOR/PARTNER/EXECUTIVE OFFICER/MEMBEREXCLUDED?","rowSpan":0,"columnSpan":3,"confidence":0,"isHeader":false,"isFooter":false},{"rowIndex":17,"columnIndex":4,"elements":["#/readResults/0/lines/147/words/0"],"boundingBox":[2.5138,6.967,2.7775,6.967,2.7775,7.1209,2.5056,7.129],"text":"N/A","rowSpan":0,"columnSpan":0,"confidence":0,"isHeader":false,"isFooter":false},{"rowIndex":17,"columnIndex":5,"elements":[],"boundingBox":[2.7775,6.967,3.0329,6.9589,3.0329,7.1128,2.7775,7.1209],"text":"","rowSpan":0,"columnSpan":0,"confidence":0,"isHeader":false,"isFooter":false},{"rowIndex":17,"columnIndex":6,"elements":[],"boundingBox":[3.0329,6.9589,4.6974,6.9102,4.6892,7.0885,3.0329,7.1128],"text":"","rowSpan":0,"columnSpan":0,"confidence":0,"isHeader":false,"isFooter":false},{"rowIndex":17,"columnIndex":7,"elements":[],"boundingBox":[4.6974,6.9102,5.3567,6.9021,5.3567,7.0804,4.6892,7.0885],"text":"","rowSpan":0,"columnSpan":0,"confidence":0,"isHeader":false,"isFooter":false},{"rowIndex":17,"columnIndex":8,"elements":[],"boundingBox":[5.3567,6.9021,6.0076,6.9021,6.0076,7.0804,5.3567,7.0804],"text":"","rowSpan":0,"columnSpan":0,"confidence":0,"isHeader":false,"isFooter":false},{"rowIndex":17,"columnIndex":9,"elements":["#/readResults/0/lines/148/words/0","#/readResults/0/lines/148/words/1","#/readResults/0/lines/148/words/2"],"boundingBox":[6.0076,6.9021,7.2684,6.9021,7.2684,7.0804,6.0076,7.0804],"text":"E.L. EACH ACCIDENT","rowSpan":0,"columnSpan":0,"confidence":0,"isHeader":false,"isFooter":false},{"rowIndex":17,"columnIndex":10,"elements":["#/readResults/0/lines/149/words/0","#/readResults/0/lines/149/words/1"],"boundingBox":[7.2684,6.9021,8.3478,6.894,8.3478,7.0723,7.2684,7.0804],"text":"$ 500,000","rowSpan":0,"columnSpan":0,"confidence":0,"isHeader":false,"isFooter":false},{"rowIndex":18,"columnIndex":0,"elements":[],"boundingBox":[0.3137,7.1371,0.5691,7.1371,0.5691,7.2344,0.3137,7.2344],"text":"","rowSpan":0,"columnSpan":0,"confidence":0,"isHeader":false,"isFooter":false},{"rowIndex":18,"columnIndex":1,"elements":["#/readResults/0/lines/150/words/0","#/readResults/0/lines/150/words/1","#/readResults/0/lines/150/words/2"],"boundingBox":[0.5691,7.1371,2.5056,7.129,2.5056,7.2425,0.5691,7.2344],"text":"(Mandatory in NH)","rowSpan":0,"columnSpan":3,"confidence":0,"isHeader":false,"isFooter":false},{"rowIndex":18,"columnIndex":4,"elements":[],"boundingBox":[2.5056,7.129,2.7775,7.1209,2.7775,7.2425,2.5056,7.2425],"text":"","rowSpan":0,"columnSpan":0,"confidence":0,"isHeader":false,"isFooter":false},{"rowIndex":18,"columnIndex":5,"elements":[],"boundingBox":[2.7775,7.1209,3.0329,7.1128,3.0329,7.2425,2.7775,7.2425],"text":"","rowSpan":0,"columnSpan":0,"confidence":0,"isHeader":false,"isFooter":false},{"rowIndex":18,"columnIndex":6,"elements":[],"boundingBox":[3.0329,7.1128,4.6892,7.0885,4.6892,7.2425,3.0329,7.2425],"text":"","rowSpan":0,"columnSpan":0,"confidence":0,"isHeader":false,"isFooter":false},{"rowIndex":18,"columnIndex":7,"elements":[],"boundingBox":[4.6892,7.0885,5.3567,7.0804,5.3567,7.2425,4.6892,7.2425],"text":"","rowSpan":0,"columnSpan":0,"confidence":0,"isHeader":false,"isFooter":false},{"rowIndex":18,"columnIndex":8,"elements":[],"boundingBox":[5.3567,7.0804,6.0076,7.0804,6.0076,7.2425,5.3567,7.2425],"text":"","rowSpan":0,"columnSpan":0,"confidence":0,"isHeader":false,"isFooter":false},{"rowIndex":18,"columnIndex":9,"elements":["#/readResults/0/lines/151/words/0","#/readResults/0/lines/151/words/1","#/readResults/0/lines/151/words/2","#/readResults/0/lines/151/words/3","#/readResults/0/lines/151/words/4"],"boundingBox":[6.0076,7.0804,7.2684,7.0804,7.2684,7.2425,6.0076,7.2425],"text":"E.L. DISEASE - EA EMPLOYEE","rowSpan":0,"columnSpan":0,"confidence":0,"isHeader":false,"isFooter":false},{"rowIndex":18,"columnIndex":10,"elements":["#/readResults/0/lines/151/words/5","#/readResults/0/lines/151/words/6"],"boundingBox":[7.2684,7.0804,8.3478,7.0723,8.3561,7.2344,7.2684,7.2425],"text":"$ 500,000","rowSpan":0,"columnSpan":0,"confidence":0,"isHeader":false,"isFooter":false},{"rowIndex":19,"columnIndex":0,"elements":[],"boundingBox":[0.3137,7.2344,0.5691,7.2344,0.5691,7.4045,0.3137,7.4045],"text":"","rowSpan":0,"columnSpan":0,"confidence":0,"isHeader":false,"isFooter":false},{"rowIndex":19,"columnIndex":1,"elements":["#/readResults/0/lines/152/words/0","#/readResults/0/lines/152/words/1","#/readResults/0/lines/152/words/2","#/readResults/0/lines/152/words/3","#/readResults/0/lines/153/words/0","#/readResults/0/lines/153/words/1","#/readResults/0/lines/153/words/2","#/readResults/0/lines/153/words/3"],"boundingBox":[0.5691,7.2344,2.5056,7.2425,2.5056,7.4045,0.5691,7.4045],"text":"If yes, describe under DESCRIPTION OF OPERATIONS below","rowSpan":0,"columnSpan":3,"confidence":0,"isHeader":false,"isFooter":false},{"rowIndex":19,"columnIndex":4,"elements":[],"boundingBox":[2.5056,7.2425,2.7775,7.2425,2.7775,7.4045,2.5056,7.4045],"text":"","rowSpan":0,"columnSpan":0,"confidence":0,"isHeader":false,"isFooter":false},{"rowIndex":19,"columnIndex":5,"elements":[],"boundingBox":[2.7775,7.2425,3.0329,7.2425,3.0329,7.3964,2.7775,7.4045],"text":"","rowSpan":0,"columnSpan":0,"confidence":0,"isHeader":false,"isFooter":false},{"rowIndex":19,"columnIndex":6,"elements":[],"boundingBox":[3.0329,7.2425,4.6892,7.2425,4.6892,7.3964,3.0329,7.3964],"text":"","rowSpan":0,"columnSpan":0,"confidence":0,"isHeader":false,"isFooter":false},{"rowIndex":19,"columnIndex":7,"elements":[],"boundingBox":[4.6892,7.2425,5.3567,7.2425,5.3567,7.3964,4.6892,7.3964],"text":"","rowSpan":0,"columnSpan":0,"confidence":0,"isHeader":false,"isFooter":false},{"rowIndex":19,"columnIndex":8,"elements":[],"boundingBox":[5.3567,7.2425,6.0076,7.2425,6.0076,7.3964,5.3567,7.3964],"text":"","rowSpan":0,"columnSpan":0,"confidence":0,"isHeader":false,"isFooter":false},{"rowIndex":19,"columnIndex":9,"elements":["#/readResults/0/lines/154/words/0","#/readResults/0/lines/154/words/1","#/readResults/0/lines/154/words/2","#/readResults/0/lines/154/words/3","#/readResults/0/lines/154/words/4"],"boundingBox":[6.0076,7.2425,7.2684,7.2425,7.2684,7.3964,6.0076,7.3964],"text":"E.L. DISEASE - POLICY LIMIT","rowSpan":0,"columnSpan":0,"confidence":0,"isHeader":false,"isFooter":false},{"rowIndex":19,"columnIndex":10,"elements":["#/readResults/0/lines/155/words/0","#/readResults/0/lines/155/words/1"],"boundingBox":[7.2684,7.2425,8.3561,7.2344,8.3561,7.3964,7.2684,7.3964],"text":"$ 500,000","rowSpan":0,"columnSpan":0,"confidence":0,"isHeader":false,"isFooter":false},{"rowIndex":20,"columnIndex":0,"elements":[],"boundingBox":[0.3137,7.4045,0.5691,7.4045,0.5774,7.9069,0.3137,7.9069],"text":"","rowSpan":2,"columnSpan":0,"confidence":0,"isHeader":false,"isFooter":false},{"rowIndex":20,"columnIndex":1,"elements":["#/readResults/0/lines/156/words/0","#/readResults/0/lines/156/words/1","#/readResults/0/lines/157/words/0"],"boundingBox":[0.5691,7.4045,1.5827,7.4045,1.5827,7.9069,0.5774,7.9069],"text":"Student Accident Abuse&Molestation","rowSpan":2,"columnSpan":2,"confidence":0,"isHeader":false,"isFooter":false},{"rowIndex":20,"columnIndex":3,"elements":[],"boundingBox":[1.5827,7.4045,2.5056,7.4045,2.5056,7.8988,1.5827,7.9069],"text":"","rowSpan":2,"columnSpan":0,"confidence":0,"isHeader":false,"isFooter":false},{"rowIndex":20,"columnIndex":4,"elements":[],"boundingBox":[2.5056,7.4045,2.7775,7.4045,2.7857,7.8988,2.5056,7.8988],"text":"","rowSpan":2,"columnSpan":0,"confidence":0,"isHeader":false,"isFooter":false},{"rowIndex":20,"columnIndex":5,"elements":[],"boundingBox":[2.7775,7.4045,3.0329,7.3964,3.0329,7.8988,2.7857,7.8988],"text":"","rowSpan":2,"columnSpan":0,"confidence":0,"isHeader":false,"isFooter":false},{"rowIndex":20,"columnIndex":6,"elements":["#/readResults/0/lines/158/words/0","#/readResults/0/lines/163/words/0"],"boundingBox":[3.0329,7.3964,4.6892,7.3964,4.6892,7.753,3.0329,7.753],"text":"99085641 MAC3142095","rowSpan":0,"columnSpan":0,"confidence":0,"isHeader":false,"isFooter":false},{"rowIndex":20,"columnIndex":7,"elements":["#/readResults/0/lines/159/words/0","#/readResults/0/lines/164/words/0"],"boundingBox":[4.6892,7.3964,5.3567,7.3964,5.3567,7.7449,4.6892,7.753],"text":"6/1/2021 6/1/2021","rowSpan":0,"columnSpan":0,"confidence":0,"isHeader":false,"isFooter":false},{"rowIndex":20,"columnIndex":8,"elements":["#/readResults/0/lines/160/words/0","#/readResults/0/lines/165/words/0"],"boundingBox":[5.3567,7.3964,6.0076,7.3964,6.0076,7.7449,5.3567,7.7449],"text":"6/1/2022 6/1/2022","rowSpan":0,"columnSpan":0,"confidence":0,"isHeader":false,"isFooter":false},{"rowIndex":20,"columnIndex":9,"elements":["#/readResults/0/lines/161/words/0","#/readResults/0/lines/161/words/1","#/readResults/0/lines/166/words/0","#/readResults/0/lines/166/words/1"],"boundingBox":[6.0076,7.3964,7.2684,7.3964,7.2684,7.7449,6.0076,7.7449],"text":"Each Occurrence Limit $1,000,000","rowSpan":0,"columnSpan":0,"confidence":0,"isHeader":false,"isFooter":false},{"rowIndex":20,"columnIndex":10,"elements":["#/readResults/0/lines/162/words/0","#/readResults/0/lines/167/words/0","#/readResults/0/lines/167/words/1"],"boundingBox":[7.2684,7.3964,8.3561,7.3964,8.3561,7.7368,7.2684,7.7449],"text":"50,000 Agg $3,000,000","rowSpan":0,"columnSpan":0,"confidence":0,"isHeader":false,"isFooter":false},{"rowIndex":21,"columnIndex":6,"elements":[],"boundingBox":[3.0329,7.753,4.6892,7.753,4.6892,7.8988,3.0329,7.8988],"text":"","rowSpan":0,"columnSpan":0,"confidence":0,"isHeader":false,"isFooter":false},{"rowIndex":21,"columnIndex":7,"elements":[],"boundingBox":[4.6892,7.753,5.3567,7.7449,5.3567,7.8988,4.6892,7.8988],"text":"","rowSpan":0,"columnSpan":0,"confidence":0,"isHeader":false,"isFooter":false},{"rowIndex":21,"columnIndex":8,"elements":[],"boundingBox":[5.3567,7.7449,6.0076,7.7449,6.0076,7.8988,5.3567,7.8988],"text":"","rowSpan":0,"columnSpan":0,"confidence":0,"isHeader":false,"isFooter":false},{"rowIndex":21,"columnIndex":9,"elements":[],"boundingBox":[6.0076,7.7449,7.2684,7.7449,7.2684,7.8988,6.0076,7.8988],"text":"","rowSpan":0,"columnSpan":0,"confidence":0,"isHeader":false,"isFooter":false},{"rowIndex":21,"columnIndex":10,"elements":[],"boundingBox":[7.2684,7.7449,8.3561,7.7368,8.3561,7.8988,7.2684,7.8988],"text":"","rowSpan":0,"columnSpan":0,"confidence":0,"isHeader":false,"isFooter":false}],"pageNumber":0,"boundingBox":[0.3268,4.0503,8.358,4.0551,8.3644,7.8961,0.3309,7.8901]}]}]